{"width":1024,"SubTexture":[{"y":1,"frameWidth":250,"x":356,"frameHeight":300,"width":175,"frameY":-32,"height":214,"name":"怪_06.png","frameX":-36},{"y":218,"frameWidth":250,"x":1,"frameHeight":300,"width":176,"frameY":-31,"height":215,"name":"怪_04.png","frameX":-36},{"y":1,"frameWidth":250,"x":179,"frameHeight":300,"width":175,"frameY":-30,"height":216,"name":"怪_08.png","frameX":-36},{"y":1,"frameWidth":250,"x":1,"frameHeight":300,"width":176,"frameY":-31,"height":215,"name":"怪_00.png","frameX":-37},{"y":219,"frameWidth":250,"x":179,"frameHeight":300,"width":175,"frameY":-32,"height":214,"name":"怪_02.png","frameX":-37}],"height":512,"name":"monster_01","imagePath":"monster_01_tex.png"}