{"frameRate":30,"name":"ui_zhuanshi_03","version":"5.5","compatibleVersion":"5.5","armature":[{"type":"Armature","frameRate":30,"name":"ui_zhuanshi_03","aabb":{"x":-22.05,"y":-21.05,"width":39,"height":52},"bone":[{"inheritScale":false,"name":"图层 1","transform":{"x":-2.55,"y":4.95}}],"slot":[{"name":"图层 1","parent":"图层 1"}],"skin":[{"slot":[{"name":"图层 1","display":[{"name":"268547518581682446.psd 资源/图层 6"},{"name":"268547518581682446.psd 资源/图层 13"},{"name":"268547518581682446.psd 资源/图层 12"},{"name":"268547518581682446.psd 资源/图层 11"},{"name":"268547518581682446.psd 资源/图层 3"},{"name":"268547518581682446.psd 资源/图层 5"},{"name":"268547518581682446.psd 资源/图层 9"},{"name":"268547518581682446.psd 资源/图层 26"}]}]}],"animation":[{"duration":14,"playTimes":0,"name":"ui_zhuanshi_03","bone":[{"name":"图层 1","translateFrame":[{"duration":2},{"duration":2,"x":-0.5,"y":0.25},{"duration":2,"x":-1,"y":0.25},{"duration":2,"x":-1,"y":0.25},{"duration":2,"y":-0.25},{"duration":2,"x":-0.25,"y":0.25},{"duration":2,"x":-1.75,"y":-0.75},{"duration":0,"x":-1.25,"y":0.25}]}],"slot":[{"name":"图层 1","displayFrame":[{"duration":2},{"duration":2,"value":1},{"duration":2,"value":2},{"duration":2,"value":3},{"duration":2,"value":4},{"duration":2,"value":5},{"duration":2,"value":6},{"duration":0,"value":7}]}]}],"defaultActions":[{"gotoAndPlay":"ui_zhuanshi_03"}]}]}